{
    "image": "48001F003202511190090.bmp",
    "width": 1296,
    "height": 609,
    "annotations": [
        {
            "label": "anomaly",
            "bbox": [
                257,
                291,
                336,
                343
            ]
        },
        {
            "label": "anomaly",
            "bbox": [
                492,
                347,
                578,
                386
            ]
        },
        {
            "label": "anomaly",
            "bbox": [
                423,
                360,
                492,
                410
            ]
        },
        {
            "label": "anomaly",
            "bbox": [
                451,
                399,
                548,
                432
            ]
        },
        {
            "label": "anomaly",
            "bbox": [
                550,
                399,
                596,
                444
            ]
        },
        {
            "label": "anomaly",
            "bbox": [
                501,
                410,
                548,
                444
            ]
        }
    ]
}