{
    "image": "48001F003202511190079.bmp",
    "width": 1308,
    "height": 601,
    "annotations": [
        {
            "label": "anomaly",
            "bbox": [
                989,
                272,
                1055,
                344
            ]
        },
        {
            "label": "anomaly",
            "bbox": [
                841,
                342,
                911,
                392
            ]
        },
        {
            "label": "anomaly",
            "bbox": [
                739,
                370,
                782,
                431
            ]
        },
        {
            "label": "anomaly",
            "bbox": [
                780,
                370,
                885,
                422
            ]
        },
        {
            "label": "anomaly",
            "bbox": [
                784,
                394,
                834,
                438
            ]
        },
        {
            "label": "anomaly",
            "bbox": [
                922,
                409,
                1015,
                446
            ]
        }
    ]
}