{
    "image": "48001F003202511190075.bmp",
    "width": 1205,
    "height": 506,
    "annotations": [
        {
            "label": "anomaly",
            "bbox": [
                990,
                178,
                1060,
                247
            ]
        },
        {
            "label": "anomaly",
            "bbox": [
                984,
                313,
                1078,
                355
            ]
        },
        {
            "label": "anomaly",
            "bbox": [
                847,
                247,
                907,
                299
            ]
        },
        {
            "label": "anomaly",
            "bbox": [
                749,
                277,
                781,
                335
            ]
        },
        {
            "label": "anomaly",
            "bbox": [
                781,
                283,
                889,
                327
            ]
        },
        {
            "label": "anomaly",
            "bbox": [
                787,
                301,
                829,
                339
            ]
        }
    ]
}